nolite/__init__.py
nolite/__main__.py
nolite/cli.py
nolite/components/__init__.py
nolite/components/extended_components.py
nolite/components/form_components.py
nolite/components/html_components.py
nolite/core/__init__.py
nolite/core/component.py
nolite/core/page.py
nolite/framework/__init__.py
nolite/framework/app.py
nolite/framework/database.py
nolite/framework/flask_app.py
nolite/nolite_starter_template/run.py
nolite/nolite_starter_template/app/__init__.py
nolite/nolite_starter_template/app/layout.py
nolite/nolite_starter_template/app/models.py
nolite/nolite_starter_template/app/routes.py
nolite/nolite_starter_template/app/static/css/style.css
nolite/utils/__init__.py
nolite/utils/scripts.py
nolite/utils/style_parser.py
nolite-0.1.1.dist-info/METADATA
nolite-0.1.1.dist-info/WHEEL
nolite-0.1.1.dist-info/entry_points.txt
nolite-0.1.1.dist-info/top_level.txt
nolite-0.1.1.dist-info/RECORD
