Metadata-Version: 2.4
Name: nolite
Version: 0.1.1
Summary: A Python library to create websites using only Python code
Home-page: https://github.com/FakeCoder01/nolite
Author: FakeCoder01
Author-email: fakecoder@duck.com
Classifier: Programming Language :: Python :: 3
Classifier: License :: OSI Approved :: MIT License
Classifier: Operating System :: OS Independent
Classifier: Intended Audience :: Developers
Classifier: Topic :: Software Development :: Libraries :: Python Modules
Classifier: Topic :: Internet :: WWW/HTTP :: Dynamic Content
Requires-Python: >=3.6
Requires-Dist: Flask<3.0.0,>=2.0.0
Requires-Dist: Flask-SQLAlchemy<3.0.0,>=2.5.1
Requires-Dist: SQLAlchemy<2.0,>=1.4
Requires-Dist: Flask-Login>=0.6.0
Requires-Dist: email_validator>=2.0.0
Dynamic: author
Dynamic: author-email
Dynamic: classifier
Dynamic: description
Dynamic: description-content-type
Dynamic: home-page
Dynamic: requires-dist
Dynamic: requires-python
Dynamic: summary
